{"cameraMode":{"drawMode":0,"name":"Shaded","section":"Shading Mode"},"sceneLighting":true,"audioPlay":false,"sceneViewState":{"m_AlwaysRefresh":true,"showFog":true,"showSkybox":true,"showFlares":true,"showImageEffects":true,"showParticleSystems":true,"showVisualEffectGraphs":true,"m_FxEnabled":true},"in2DMode":false,"pivot":{"x":-3.533236026763916,"y":4.5337233543396,"z":-2.706516981124878},"rotation":{"x":-0.2712392210960388,"y":-0.15469400584697724,"z":0.04236609861254692,"w":-0.9501091241836548},"size":0.8660253882408142,"orthographic":false}